AUTHORS.rst
CONTRIBUTING.rst
HISTORY.rst
LICENSE
MANIFEST.in
README.rst
setup.cfg
setup.py
hyperpoints/__init__.py
hyperpoints/hyperpoints.py
hyperpoints.egg-info/PKG-INFO
hyperpoints.egg-info/SOURCES.txt
hyperpoints.egg-info/dependency_links.txt
hyperpoints.egg-info/not-zip-safe
hyperpoints.egg-info/top_level.txt
test/__init__.py
test/test_hyperpoints.py