Metadata-Version: 1.1
Name: hyperpoints
Version: 0.0.1
Summary: Distributed hyperparameter optimization and reinforcement learning algorithms.
Home-page: https://github.com/yngtodd/hyperpoints
Author: Todd Young
Author-email: youngmt1@ornl.gov
License: MIT
Keywords: hyperpoints
Platform: UNKNOWN
Classifier: Development Status :: 2 - Pre-Alpha
Classifier: Intended Audience :: Developers
Classifier: License :: OSI Approved :: MIT License
Classifier: Natural Language :: English
Classifier: Programming Language :: Python :: 3.6
Classifier: Programming Language :: Python :: Implementation :: PyPy
